elixir_client/__init__.py
elixir_client/config.py
elixir_client/core.py
elixir_client/decorators.py
elixir_client/dn_tracer.py
elixir_client/file_uploader.py
elixir_client/output/__init__.py
elixir_client/output/results_handler.py
elixir_client/utils/__init__.py
elixir_client/utils/audio_utils.py
elixir_client/utils/file_type_classifier.py
tests/__init__.py
tests/test_audio_utils.py
tests/test_core.py
tests/test_registration.py
tests/test_results_handler.py
elixir_client-0.7.7.dist-info/LICENSE.md
elixir_client-0.7.7.dist-info/METADATA
elixir_client-0.7.7.dist-info/WHEEL
elixir_client-0.7.7.dist-info/entry_points.txt
elixir_client-0.7.7.dist-info/top_level.txt
elixir_client-0.7.7.dist-info/RECORD
